pyasn1_ldap/__init__.py
pyasn1_ldap/rfc4511.py
pyasn1_ldap-0.1.0.dist-info/LICENSE
pyasn1_ldap-0.1.0.dist-info/METADATA
pyasn1_ldap-0.1.0.dist-info/WHEEL
pyasn1_ldap-0.1.0.dist-info/top_level.txt
pyasn1_ldap-0.1.0.dist-info/RECORD
